<annotation>
	<folder>smoke-dataset</folder>
	<filename>damon-lam-iQTPNZoaRNU-unsplash.jpg</filename>
	<path>D:\Ignis-fire-detection-and-mitigation-system\dataset\smoke-dataset\damon-lam-iQTPNZoaRNU-unsplash.jpg</path>
	<source>
		<database>Unknown</database>
	</source>
	<size>
		<width>3456</width>
		<height>5184</height>
		<depth>3</depth>
	</size>
	<segmented>0</segmented>
	<object>
		<name>Smoke</name>
		<pose>Unspecified</pose>
		<truncated>0</truncated>
		<difficult>0</difficult>
		<bndbox>
			<xmin>378</xmin>
			<ymin>773</ymin>
			<xmax>2066</xmax>
			<ymax>4160</ymax>
		</bndbox>
	</object>
</annotation>
